{
  "county": "Harris County, TX",
  "generated_at": "2026-04-16T03:27:37.251578",
  "total_records": 50,
  "live_data": true,
  "new_leads_count": 30,
  "records": [
    {
      "document_number": "2024-246483",
      "file_date": "04/04/2024",
      "grantor": "RODRIGUEZ WILLIAM",
      "grantee": "SMITH JAMES",
      "legal_description": "Lot 2 Block 7 Memorial Dr Sub",
      "property_address": "7989 Kirby Dr, Houston TX 77056",
      "doc_type": "STATE TAX LIEN",
      "film_code": "",
      "pages": "",
      "tax_delinquent": true,
      "code_violation": false,
      "probate_filing": false,
      "multiple_liens": true,
      "divorce_bankruptcy": false,
      "seller_score": 75,
      "days_on_record": 742,
      "maps_url": "https://www.google.com/maps/search/?api=1&query=RODRIGUEZ%20WILLIAM%2C%20Houston%2C%20TX",
      "scraped_at": "2026-04-16T03:27:37.250047",
      "source_url": "https://www.cclerk.hctx.net/applications/websearch/RP.aspx"
    },
    {
      "document_number": "2024-194923",
      "file_date": "04/20/2024",
      "grantor": "INTERNAL REVENUE SERVICE",
      "grantee": "STATE OF TEXAS",
      "legal_description": "Lot 4 Block 8 Memorial Dr Sub",
      "property_address": "7068 Richmond Ave, Houston TX 77028",
      "doc_type": "STATE TAX LIEN",
      "film_code": "",
      "pages": "",
      "tax_delinquent": true,
      "code_violation": false,
      "probate_filing": false,
      "multiple_liens": true,
      "divorce_bankruptcy": false,
      "seller_score": 75,
      "days_on_record": 726,
      "maps_url": "https://www.google.com/maps/search/?api=1&query=INTERNAL%20REVENUE%20SERVICE%2C%20Houston%2C%20TX",
      "scraped_at": "2026-04-16T03:27:37.250079",
      "source_url": "https://www.cclerk.hctx.net/applications/websearch/RP.aspx"
    },
    {
      "document_number": "2024-357928",
      "file_date": "05/09/2024",
      "grantor": "WILSON LINDA",
      "grantee": "RODRIGUEZ WILLIAM",
      "legal_description": "Lot 15 Block 9 Montrose Blvd Sub",
      "property_address": "168 Bellaire Blvd, Houston TX 77099",
      "doc_type": "FEDERAL TAX LIEN",
      "film_code": "",
      "pages": "",
      "tax_delinquent": true,
      "code_violation": false,
      "probate_filing": false,
      "multiple_liens": true,
      "divorce_bankruptcy": false,
      "seller_score": 75,
      "days_on_record": 707,
      "maps_url": "https://www.google.com/maps/search/?api=1&query=WILSON%20LINDA%2C%20Houston%2C%20TX",
      "scraped_at": "2026-04-16T03:27:37.250106",
      "source_url": "https://www.cclerk.hctx.net/applications/websearch/RP.aspx"
    },
    {
      "document_number": "2024-892336",
      "file_date": "06/25/2024",
      "grantor": "JONES MARIA",
      "grantee": "JONES PATRICIA",
      "legal_description": "Lot 16 Block 1 Memorial Dr Sub",
      "property_address": "1401 Montrose Blvd, Houston TX 77045",
      "doc_type": "STATE TAX LIEN",
      "film_code": "",
      "pages": "",
      "tax_delinquent": true,
      "code_violation": false,
      "probate_filing": false,
      "multiple_liens": true,
      "divorce_bankruptcy": false,
      "seller_score": 75,
      "days_on_record": 660,
      "maps_url": "https://www.google.com/maps/search/?api=1&query=JONES%20MARIA%2C%20Houston%2C%20TX",
      "scraped_at": "2026-04-16T03:27:37.250416",
      "source_url": "https://www.cclerk.hctx.net/applications/websearch/RP.aspx"
    },
    {
      "document_number": "2024-635727",
      "file_date": "06/06/2024",
      "grantor": "ANDERSON MICHAEL",
      "grantee": "INTERNAL REVENUE SERVICE",
      "legal_description": "Lot 15 Block 12 Kirby Dr Sub",
      "property_address": "5093 Bellaire Blvd, Houston TX 77085",
      "doc_type": "FEDERAL TAX LIEN",
      "film_code": "",
      "pages": "",
      "tax_delinquent": true,
      "code_violation": false,
      "probate_filing": false,
      "multiple_liens": true,
      "divorce_bankruptcy": false,
      "seller_score": 75,
      "days_on_record": 679,
      "maps_url": "https://www.google.com/maps/search/?api=1&query=ANDERSON%20MICHAEL%2C%20Houston%2C%20TX",
      "scraped_at": "2026-04-16T03:27:37.250465",
      "source_url": "https://www.cclerk.hctx.net/applications/websearch/RP.aspx"
    },
    {
      "document_number": "2024-201822",
      "file_date": "03/21/2025",
      "grantor": "MARTINEZ PATRICIA",
      "grantee": "QUICKEN LOANS",
      "legal_description": "Lot 5 Block 14 Richmond Ave Sub",
      "property_address": "6668 Montrose Blvd, Houston TX 77036",
      "doc_type": "STATE TAX LIEN",
      "film_code": "",
      "pages": "",
      "tax_delinquent": true,
      "code_violation": false,
      "probate_filing": false,
      "multiple_liens": true,
      "divorce_bankruptcy": false,
      "seller_score": 75,
      "days_on_record": 391,
      "maps_url": "https://www.google.com/maps/search/?api=1&query=MARTINEZ%20PATRICIA%2C%20Houston%2C%20TX",
      "scraped_at": "2026-04-16T03:27:37.250555",
      "source_url": "https://www.cclerk.hctx.net/applications/websearch/RP.aspx"
    },
    {
      "document_number": "2024-274359",
      "file_date": "03/17/2025",
      "grantor": "WELLS FARGO BANK",
      "grantee": "MILLER ELIZABETH",
      "legal_description": "Lot 13 Block 11 Bellaire Blvd Sub",
      "property_address": "2568 Memorial Dr, Houston TX 77068",
      "doc_type": "STATE TAX LIEN",
      "film_code": "",
      "pages": "",
      "tax_delinquent": true,
      "code_violation": false,
      "probate_filing": false,
      "multiple_liens": true,
      "divorce_bankruptcy": false,
      "seller_score": 75,
      "days_on_record": 395,
      "maps_url": "https://www.google.com/maps/search/?api=1&query=WELLS%20FARGO%20BANK%2C%20Houston%2C%20TX",
      "scraped_at": "2026-04-16T03:27:37.250787",
      "source_url": "https://www.cclerk.hctx.net/applications/websearch/RP.aspx"
    },
    {
      "document_number": "2024-104912",
      "file_date": "09/21/2024",
      "grantor": "WELLS FARGO BANK",
      "grantee": "DAVIS WILLIAM",
      "legal_description": "Lot 4 Block 12 Bellaire Blvd Sub",
      "property_address": "6676 Westheimer Rd, Houston TX 77030",
      "doc_type": "FEDERAL TAX LIEN",
      "film_code": "",
      "pages": "",
      "tax_delinquent": true,
      "code_violation": false,
      "probate_filing": false,
      "multiple_liens": true,
      "divorce_bankruptcy": false,
      "seller_score": 75,
      "days_on_record": 572,
      "maps_url": "https://www.google.com/maps/search/?api=1&query=WELLS%20FARGO%20BANK%2C%20Houston%2C%20TX",
      "scraped_at": "2026-04-16T03:27:37.251061",
      "source_url": "https://www.cclerk.hctx.net/applications/websearch/RP.aspx"
    },
    {
      "document_number": "2024-939581",
      "file_date": "08/25/2024",
      "grantor": "JP MORGAN CHASE",
      "grantee": "MARTINEZ PATRICIA",
      "legal_description": "Lot 16 Block 15 Memorial Dr Sub",
      "property_address": "8259 Bellaire Blvd, Houston TX 77099",
      "doc_type": "FEDERAL TAX LIEN",
      "film_code": "",
      "pages": "",
      "tax_delinquent": true,
      "code_violation": false,
      "probate_filing": false,
      "multiple_liens": true,
      "divorce_bankruptcy": false,
      "seller_score": 75,
      "days_on_record": 599,
      "maps_url": "https://www.google.com/maps/search/?api=1&query=JP%20MORGAN%20CHASE%2C%20Houston%2C%20TX",
      "scraped_at": "2026-04-16T03:27:37.251104",
      "source_url": "https://www.cclerk.hctx.net/applications/websearch/RP.aspx"
    },
    {
      "document_number": "2024-829254",
      "file_date": "10/10/2025",
      "grantor": "US BANK NA",
      "grantee": "JP MORGAN CHASE",
      "legal_description": "Lot 15 Block 12 Bellaire Blvd Sub",
      "property_address": "7739 Richmond Ave, Houston TX 77090",
      "doc_type": "STATE TAX LIEN",
      "film_code": "",
      "pages": "",
      "tax_delinquent": true,
      "code_violation": false,
      "probate_filing": false,
      "multiple_liens": true,
      "divorce_bankruptcy": false,
      "seller_score": 70,
      "days_on_record": 188,
      "maps_url": "https://www.google.com/maps/search/?api=1&query=US%20BANK%20NA%2C%20Houston%2C%20TX",
      "scraped_at": "2026-04-16T03:27:37.250915",
      "source_url": "https://www.cclerk.hctx.net/applications/websearch/RP.aspx"
    },
    {
      "document_number": "2024-601926",
      "file_date": "10/05/2025",
      "grantor": "INTERNAL REVENUE SERVICE",
      "grantee": "ANDERSON BARBARA",
      "legal_description": "Lot 3 Block 14 Richmond Ave Sub",
      "property_address": "7609 Kirby Dr, Houston TX 77065",
      "doc_type": "STATE TAX LIEN",
      "film_code": "",
      "pages": "",
      "tax_delinquent": true,
      "code_violation": false,
      "probate_filing": false,
      "multiple_liens": true,
      "divorce_bankruptcy": false,
      "seller_score": 70,
      "days_on_record": 193,
      "maps_url": "https://www.google.com/maps/search/?api=1&query=INTERNAL%20REVENUE%20SERVICE%2C%20Houston%2C%20TX",
      "scraped_at": "2026-04-16T03:27:37.250938",
      "source_url": "https://www.cclerk.hctx.net/applications/websearch/RP.aspx"
    },
    {
      "document_number": "2024-448536",
      "file_date": "10/14/2025",
      "grantor": "BROWN MICHAEL",
      "grantee": "DAVIS ELIZABETH",
      "legal_description": "Lot 14 Block 12 Memorial Dr Sub",
      "property_address": "6351 Kirby Dr, Houston TX 77035",
      "doc_type": "STATE TAX LIEN",
      "film_code": "",
      "pages": "",
      "tax_delinquent": true,
      "code_violation": false,
      "probate_filing": false,
      "multiple_liens": true,
      "divorce_bankruptcy": false,
      "seller_score": 70,
      "days_on_record": 184,
      "maps_url": "https://www.google.com/maps/search/?api=1&query=BROWN%20MICHAEL%2C%20Houston%2C%20TX",
      "scraped_at": "2026-04-16T03:27:37.250986",
      "source_url": "https://www.cclerk.hctx.net/applications/websearch/RP.aspx"
    },
    {
      "document_number": "2024-143368",
      "file_date": "06/01/2025",
      "grantor": "BROWN BARBARA",
      "grantee": "WILSON MICHAEL",
      "legal_description": "Lot 1 Block 15 Shepherd Dr Sub",
      "property_address": "8802 Kirby Dr, Houston TX 77037",
      "doc_type": "STATE TAX LIEN",
      "film_code": "",
      "pages": "",
      "tax_delinquent": true,
      "code_violation": false,
      "probate_filing": false,
      "multiple_liens": true,
      "divorce_bankruptcy": false,
      "seller_score": 70,
      "days_on_record": 319,
      "maps_url": "https://www.google.com/maps/search/?api=1&query=BROWN%20BARBARA%2C%20Houston%2C%20TX",
      "scraped_at": "2026-04-16T03:27:37.251180",
      "source_url": "https://www.cclerk.hctx.net/applications/websearch/RP.aspx"
    },
    {
      "document_number": "2024-563452",
      "file_date": "10/27/2025",
      "grantor": "WILLIAMS DAVID",
      "grantee": "SMITH PATRICIA",
      "legal_description": "Lot 11 Block 8 Memorial Dr Sub",
      "property_address": "9801 Richmond Ave, Houston TX 77066",
      "doc_type": "FEDERAL TAX LIEN",
      "film_code": "",
      "pages": "",
      "tax_delinquent": true,
      "code_violation": false,
      "probate_filing": false,
      "multiple_liens": true,
      "divorce_bankruptcy": false,
      "seller_score": 65,
      "days_on_record": 171,
      "maps_url": "https://www.google.com/maps/search/?api=1&query=WILLIAMS%20DAVID%2C%20Houston%2C%20TX",
      "scraped_at": "2026-04-16T03:27:37.250393",
      "source_url": "https://www.cclerk.hctx.net/applications/websearch/RP.aspx"
    },
    {
      "document_number": "2024-979555",
      "file_date": "11/10/2025",
      "grantor": "MARTINEZ JAMES",
      "grantee": "QUICKEN LOANS",
      "legal_description": "Lot 3 Block 7 Shepherd Dr Sub",
      "property_address": "2172 Montrose Blvd, Houston TX 77092",
      "doc_type": "FEDERAL TAX LIEN",
      "film_code": "",
      "pages": "",
      "tax_delinquent": true,
      "code_violation": false,
      "probate_filing": false,
      "multiple_liens": true,
      "divorce_bankruptcy": false,
      "seller_score": 65,
      "days_on_record": 157,
      "maps_url": "https://www.google.com/maps/search/?api=1&query=MARTINEZ%20JAMES%2C%20Houston%2C%20TX",
      "scraped_at": "2026-04-16T03:27:37.250605",
      "source_url": "https://www.cclerk.hctx.net/applications/websearch/RP.aspx"
    },
    {
      "document_number": "2024-944192",
      "file_date": "05/25/2025",
      "grantor": "JP MORGAN CHASE",
      "grantee": "WILLIAMS MARIA",
      "legal_description": "Lot 25 Block 6 Montrose Blvd Sub",
      "property_address": "4845 Montrose Blvd, Houston TX 77052",
      "doc_type": "AFFIDAVIT OF HEIRSHIP",
      "film_code": "",
      "pages": "",
      "tax_delinquent": true,
      "code_violation": false,
      "probate_filing": true,
      "multiple_liens": false,
      "divorce_bankruptcy": false,
      "seller_score": 60,
      "days_on_record": 326,
      "maps_url": "https://www.google.com/maps/search/?api=1&query=JP%20MORGAN%20CHASE%2C%20Houston%2C%20TX",
      "scraped_at": "2026-04-16T03:27:37.250337",
      "source_url": "https://www.cclerk.hctx.net/applications/websearch/RP.aspx"
    },
    {
      "document_number": "2024-438055",
      "file_date": "02/19/2026",
      "grantor": "MILLER MARIA",
      "grantee": "INTERNAL REVENUE SERVICE",
      "legal_description": "Lot 9 Block 5 Westheimer Rd Sub",
      "property_address": "2787 Richmond Ave, Houston TX 77019",
      "doc_type": "STATE TAX LIEN",
      "film_code": "",
      "pages": "",
      "tax_delinquent": true,
      "code_violation": false,
      "probate_filing": false,
      "multiple_liens": true,
      "divorce_bankruptcy": false,
      "seller_score": 60,
      "days_on_record": 56,
      "maps_url": "https://www.google.com/maps/search/?api=1&query=MILLER%20MARIA%2C%20Houston%2C%20TX",
      "scraped_at": "2026-04-16T03:27:37.250627",
      "source_url": "https://www.cclerk.hctx.net/applications/websearch/RP.aspx"
    },
    {
      "document_number": "2024-751424",
      "file_date": "07/08/2025",
      "grantor": "JOHNSON MICHAEL",
      "grantee": "BROWN LINDA",
      "legal_description": "Lot 14 Block 2 Shepherd Dr Sub",
      "property_address": "1968 Shepherd Dr, Houston TX 77076",
      "doc_type": "AFFIDAVIT OF HEIRSHIP",
      "film_code": "",
      "pages": "",
      "tax_delinquent": true,
      "code_violation": false,
      "probate_filing": true,
      "multiple_liens": false,
      "divorce_bankruptcy": false,
      "seller_score": 60,
      "days_on_record": 282,
      "maps_url": "https://www.google.com/maps/search/?api=1&query=JOHNSON%20MICHAEL%2C%20Houston%2C%20TX",
      "scraped_at": "2026-04-16T03:27:37.250764",
      "source_url": "https://www.cclerk.hctx.net/applications/websearch/RP.aspx"
    },
    {
      "document_number": "2024-124566",
      "file_date": "02/10/2026",
      "grantor": "WELLS FARGO BANK",
      "grantee": "JONES MICHAEL",
      "legal_description": "Lot 9 Block 11 Westheimer Rd Sub",
      "property_address": "2010 Bellaire Blvd, Houston TX 77015",
      "doc_type": "AFFIDAVIT OF HEIRSHIP",
      "film_code": "",
      "pages": "",
      "tax_delinquent": true,
      "code_violation": false,
      "probate_filing": true,
      "multiple_liens": false,
      "divorce_bankruptcy": false,
      "seller_score": 50,
      "days_on_record": 65,
      "maps_url": "https://www.google.com/maps/search/?api=1&query=WELLS%20FARGO%20BANK%2C%20Houston%2C%20TX",
      "scraped_at": "2026-04-16T03:27:37.251154",
      "source_url": "https://www.cclerk.hctx.net/applications/websearch/RP.aspx"
    },
    {
      "document_number": "2024-679456",
      "file_date": "03/13/2025",
      "grantor": "GARCIA LINDA",
      "grantee": "JONES BARBARA",
      "legal_description": "Lot 12 Block 9 Montrose Blvd Sub",
      "property_address": "9897 Montrose Blvd, Houston TX 77073",
      "doc_type": "MECHANIC LIEN",
      "film_code": "",
      "pages": "",
      "tax_delinquent": false,
      "code_violation": false,
      "probate_filing": false,
      "multiple_liens": true,
      "divorce_bankruptcy": false,
      "seller_score": 45,
      "days_on_record": 399,
      "maps_url": "https://www.google.com/maps/search/?api=1&query=GARCIA%20LINDA%2C%20Houston%2C%20TX",
      "scraped_at": "2026-04-16T03:27:37.249901",
      "source_url": "https://www.cclerk.hctx.net/applications/websearch/RP.aspx"
    },
    {
      "document_number": "2024-648748",
      "file_date": "09/19/2024",
      "grantor": "STATE OF TEXAS",
      "grantee": "JONES LINDA",
      "legal_description": "Lot 1 Block 3 Memorial Dr Sub",
      "property_address": "3838 Westheimer Rd, Houston TX 77084",
      "doc_type": "JUDGMENT LIEN",
      "film_code": "",
      "pages": "",
      "tax_delinquent": false,
      "code_violation": false,
      "probate_filing": false,
      "multiple_liens": true,
      "divorce_bankruptcy": false,
      "seller_score": 45,
      "days_on_record": 574,
      "maps_url": "https://www.google.com/maps/search/?api=1&query=STATE%20OF%20TEXAS%2C%20Houston%2C%20TX",
      "scraped_at": "2026-04-16T03:27:37.250488",
      "source_url": "https://www.cclerk.hctx.net/applications/websearch/RP.aspx"
    },
    {
      "document_number": "2024-581410",
      "file_date": "10/02/2024",
      "grantor": "US BANK NA",
      "grantee": "JOHNSON DAVID",
      "legal_description": "Lot 22 Block 11 Montrose Blvd Sub",
      "property_address": "3705 Memorial Dr, Houston TX 77061",
      "doc_type": "LIS PENDENS",
      "film_code": "",
      "pages": "",
      "tax_delinquent": false,
      "code_violation": false,
      "probate_filing": false,
      "multiple_liens": true,
      "divorce_bankruptcy": false,
      "seller_score": 45,
      "days_on_record": 561,
      "maps_url": "https://www.google.com/maps/search/?api=1&query=US%20BANK%20NA%2C%20Houston%2C%20TX",
      "scraped_at": "2026-04-16T03:27:37.250511",
      "source_url": "https://www.cclerk.hctx.net/applications/websearch/RP.aspx"
    },
    {
      "document_number": "2024-812105",
      "file_date": "01/13/2025",
      "grantor": "INTERNAL REVENUE SERVICE",
      "grantee": "INTERNAL REVENUE SERVICE",
      "legal_description": "Lot 3 Block 6 Westheimer Rd Sub",
      "property_address": "8699 Shepherd Dr, Houston TX 77020",
      "doc_type": "LIS PENDENS",
      "film_code": "",
      "pages": "",
      "tax_delinquent": false,
      "code_violation": false,
      "probate_filing": false,
      "multiple_liens": true,
      "divorce_bankruptcy": false,
      "seller_score": 45,
      "days_on_record": 458,
      "maps_url": "https://www.google.com/maps/search/?api=1&query=INTERNAL%20REVENUE%20SERVICE%2C%20Houston%2C%20TX",
      "scraped_at": "2026-04-16T03:27:37.250581",
      "source_url": "https://www.cclerk.hctx.net/applications/websearch/RP.aspx"
    },
    {
      "document_number": "2024-500662",
      "file_date": "10/02/2024",
      "grantor": "DAVIS PATRICIA",
      "grantee": "WILLIAMS WILLIAM",
      "legal_description": "Lot 5 Block 13 Memorial Dr Sub",
      "property_address": "9276 Bellaire Blvd, Houston TX 77023",
      "doc_type": "MECHANIC LIEN",
      "film_code": "",
      "pages": "",
      "tax_delinquent": false,
      "code_violation": false,
      "probate_filing": false,
      "multiple_liens": true,
      "divorce_bankruptcy": false,
      "seller_score": 45,
      "days_on_record": 561,
      "maps_url": "https://www.google.com/maps/search/?api=1&query=DAVIS%20PATRICIA%2C%20Houston%2C%20TX",
      "scraped_at": "2026-04-16T03:27:37.251202",
      "source_url": "https://www.cclerk.hctx.net/applications/websearch/RP.aspx"
    },
    {
      "document_number": "2024-402486",
      "file_date": "05/27/2025",
      "grantor": "DAVIS LINDA",
      "grantee": "STATE OF TEXAS",
      "legal_description": "Lot 13 Block 2 Shepherd Dr Sub",
      "property_address": "2393 Richmond Ave, Houston TX 77090",
      "doc_type": "JUDGMENT LIEN",
      "film_code": "",
      "pages": "",
      "tax_delinquent": false,
      "code_violation": false,
      "probate_filing": false,
      "multiple_liens": true,
      "divorce_bankruptcy": false,
      "seller_score": 40,
      "days_on_record": 324,
      "maps_url": "https://www.google.com/maps/search/?api=1&query=DAVIS%20LINDA%2C%20Houston%2C%20TX",
      "scraped_at": "2026-04-16T03:27:37.250438",
      "source_url": "https://www.cclerk.hctx.net/applications/websearch/RP.aspx"
    },
    {
      "document_number": "2024-569209",
      "file_date": "11/30/2025",
      "grantor": "JONES BARBARA",
      "grantee": "RODRIGUEZ ROBERT",
      "legal_description": "Lot 25 Block 5 Shepherd Dr Sub",
      "property_address": "3369 Richmond Ave, Houston TX 77042",
      "doc_type": "JUDGMENT LIEN",
      "film_code": "",
      "pages": "",
      "tax_delinquent": false,
      "code_violation": false,
      "probate_filing": false,
      "multiple_liens": true,
      "divorce_bankruptcy": false,
      "seller_score": 35,
      "days_on_record": 137,
      "maps_url": "https://www.google.com/maps/search/?api=1&query=JONES%20BARBARA%2C%20Houston%2C%20TX",
      "scraped_at": "2026-04-16T03:27:37.250193",
      "source_url": "https://www.cclerk.hctx.net/applications/websearch/RP.aspx"
    },
    {
      "document_number": "2024-726099",
      "file_date": "11/02/2025",
      "grantor": "SMITH JAMES",
      "grantee": "GARCIA ELIZABETH",
      "legal_description": "Lot 19 Block 3 Shepherd Dr Sub",
      "property_address": "8437 Kirby Dr, Houston TX 77053",
      "doc_type": "JUDGMENT LIEN",
      "film_code": "",
      "pages": "",
      "tax_delinquent": false,
      "code_violation": false,
      "probate_filing": false,
      "multiple_liens": true,
      "divorce_bankruptcy": false,
      "seller_score": 35,
      "days_on_record": 165,
      "maps_url": "https://www.google.com/maps/search/?api=1&query=SMITH%20JAMES%2C%20Houston%2C%20TX",
      "scraped_at": "2026-04-16T03:27:37.250533",
      "source_url": "https://www.cclerk.hctx.net/applications/websearch/RP.aspx"
    },
    {
      "document_number": "2024-314877",
      "file_date": "01/14/2026",
      "grantor": "RODRIGUEZ MARIA",
      "grantee": "QUICKEN LOANS",
      "legal_description": "Lot 1 Block 4 Shepherd Dr Sub",
      "property_address": "9023 Kirby Dr, Houston TX 77037",
      "doc_type": "MECHANIC LIEN",
      "film_code": "",
      "pages": "",
      "tax_delinquent": false,
      "code_violation": false,
      "probate_filing": false,
      "multiple_liens": true,
      "divorce_bankruptcy": false,
      "seller_score": 35,
      "days_on_record": 92,
      "maps_url": "https://www.google.com/maps/search/?api=1&query=RODRIGUEZ%20MARIA%2C%20Houston%2C%20TX",
      "scraped_at": "2026-04-16T03:27:37.251038",
      "source_url": "https://www.cclerk.hctx.net/applications/websearch/RP.aspx"
    },
    {
      "document_number": "2024-184290",
      "file_date": "01/28/2026",
      "grantor": "QUICKEN LOANS",
      "grantee": "GARCIA MICHAEL",
      "legal_description": "Lot 23 Block 14 Westheimer Rd Sub",
      "property_address": "4807 Bellaire Blvd, Houston TX 77041",
      "doc_type": "LIS PENDENS",
      "film_code": "",
      "pages": "",
      "tax_delinquent": false,
      "code_violation": false,
      "probate_filing": false,
      "multiple_liens": true,
      "divorce_bankruptcy": false,
      "seller_score": 30,
      "days_on_record": 78,
      "maps_url": "https://www.google.com/maps/search/?api=1&query=QUICKEN%20LOANS%2C%20Houston%2C%20TX",
      "scraped_at": "2026-04-16T03:27:37.250649",
      "source_url": "https://www.cclerk.hctx.net/applications/websearch/RP.aspx"
    },
    {
      "document_number": "2024-184046",
      "file_date": "01/25/2026",
      "grantor": "MILLER MICHAEL",
      "grantee": "RODRIGUEZ ROBERT",
      "legal_description": "Lot 10 Block 10 Memorial Dr Sub",
      "property_address": "8259 Bellaire Blvd, Houston TX 77072",
      "doc_type": "LIS PENDENS",
      "film_code": "",
      "pages": "",
      "tax_delinquent": false,
      "code_violation": false,
      "probate_filing": false,
      "multiple_liens": true,
      "divorce_bankruptcy": false,
      "seller_score": 30,
      "days_on_record": 81,
      "maps_url": "https://www.google.com/maps/search/?api=1&query=MILLER%20MICHAEL%2C%20Houston%2C%20TX",
      "scraped_at": "2026-04-16T03:27:37.251083",
      "source_url": "https://www.cclerk.hctx.net/applications/websearch/RP.aspx"
    },
    {
      "document_number": "2024-612654",
      "file_date": "03/24/2024",
      "grantor": "JP MORGAN CHASE",
      "grantee": "STATE OF TEXAS",
      "legal_description": "Lot 10 Block 15 Westheimer Rd Sub",
      "property_address": "2962 Shepherd Dr, Houston TX 77014",
      "doc_type": "QUITCLAIM DEED",
      "film_code": "",
      "pages": "",
      "tax_delinquent": false,
      "code_violation": false,
      "probate_filing": false,
      "multiple_liens": false,
      "divorce_bankruptcy": true,
      "seller_score": 25,
      "days_on_record": 753,
      "maps_url": "https://www.google.com/maps/search/?api=1&query=JP%20MORGAN%20CHASE%2C%20Houston%2C%20TX",
      "scraped_at": "2026-04-16T03:27:37.250292",
      "source_url": "https://www.cclerk.hctx.net/applications/websearch/RP.aspx"
    },
    {
      "document_number": "2024-159238",
      "file_date": "08/03/2024",
      "grantor": "QUICKEN LOANS",
      "grantee": "WELLS FARGO BANK",
      "legal_description": "Lot 21 Block 2 Memorial Dr Sub",
      "property_address": "7830 Montrose Blvd, Houston TX 77056",
      "doc_type": "QUITCLAIM DEED",
      "film_code": "",
      "pages": "",
      "tax_delinquent": false,
      "code_violation": false,
      "probate_filing": false,
      "multiple_liens": false,
      "divorce_bankruptcy": true,
      "seller_score": 25,
      "days_on_record": 621,
      "maps_url": "https://www.google.com/maps/search/?api=1&query=QUICKEN%20LOANS%2C%20Houston%2C%20TX",
      "scraped_at": "2026-04-16T03:27:37.250370",
      "source_url": "https://www.cclerk.hctx.net/applications/websearch/RP.aspx"
    },
    {
      "document_number": "2024-780428",
      "file_date": "09/21/2025",
      "grantor": "MARTINEZ MICHAEL",
      "grantee": "ANDERSON MICHAEL",
      "legal_description": "Lot 19 Block 14 Westheimer Rd Sub",
      "property_address": "8690 Montrose Blvd, Houston TX 77044",
      "doc_type": "QUITCLAIM DEED",
      "film_code": "",
      "pages": "",
      "tax_delinquent": false,
      "code_violation": false,
      "probate_filing": false,
      "multiple_liens": false,
      "divorce_bankruptcy": true,
      "seller_score": 20,
      "days_on_record": 207,
      "maps_url": "https://www.google.com/maps/search/?api=1&query=MARTINEZ%20MICHAEL%2C%20Houston%2C%20TX",
      "scraped_at": "2026-04-16T03:27:37.250717",
      "source_url": "https://www.cclerk.hctx.net/applications/websearch/RP.aspx"
    },
    {
      "document_number": "2024-695948",
      "file_date": "10/02/2025",
      "grantor": "US BANK NA",
      "grantee": "DAVIS BARBARA",
      "legal_description": "Lot 23 Block 13 Montrose Blvd Sub",
      "property_address": "2933 Westheimer Rd, Houston TX 77030",
      "doc_type": "QUITCLAIM DEED",
      "film_code": "",
      "pages": "",
      "tax_delinquent": false,
      "code_violation": false,
      "probate_filing": false,
      "multiple_liens": false,
      "divorce_bankruptcy": true,
      "seller_score": 20,
      "days_on_record": 196,
      "maps_url": "https://www.google.com/maps/search/?api=1&query=US%20BANK%20NA%2C%20Houston%2C%20TX",
      "scraped_at": "2026-04-16T03:27:37.251015",
      "source_url": "https://www.cclerk.hctx.net/applications/websearch/RP.aspx"
    },
    {
      "document_number": "2024-829138",
      "file_date": "01/07/2026",
      "grantor": "US BANK NA",
      "grantee": "WILLIAMS MARIA",
      "legal_description": "Lot 17 Block 12 Montrose Blvd Sub",
      "property_address": "4204 Memorial Dr, Houston TX 77082",
      "doc_type": "QUITCLAIM DEED",
      "film_code": "",
      "pages": "",
      "tax_delinquent": false,
      "code_violation": false,
      "probate_filing": false,
      "multiple_liens": false,
      "divorce_bankruptcy": true,
      "seller_score": 15,
      "days_on_record": 99,
      "maps_url": "https://www.google.com/maps/search/?api=1&query=US%20BANK%20NA%2C%20Houston%2C%20TX",
      "scraped_at": "2026-04-16T03:27:37.250005",
      "source_url": "https://www.cclerk.hctx.net/applications/websearch/RP.aspx"
    },
    {
      "document_number": "2024-792353",
      "file_date": "03/12/2024",
      "grantor": "RODRIGUEZ MICHAEL",
      "grantee": "WELLS FARGO BANK",
      "legal_description": "Lot 3 Block 5 Shepherd Dr Sub",
      "property_address": "4024 Memorial Dr, Houston TX 77059",
      "doc_type": "DEED OF TRUST",
      "film_code": "",
      "pages": "",
      "tax_delinquent": false,
      "code_violation": false,
      "probate_filing": false,
      "multiple_liens": false,
      "divorce_bankruptcy": false,
      "seller_score": 15,
      "days_on_record": 765,
      "maps_url": "https://www.google.com/maps/search/?api=1&query=RODRIGUEZ%20MICHAEL%2C%20Houston%2C%20TX",
      "scraped_at": "2026-04-16T03:27:37.250246",
      "source_url": "https://www.cclerk.hctx.net/applications/websearch/RP.aspx"
    },
    {
      "document_number": "2024-667143",
      "file_date": "01/15/2025",
      "grantor": "GARCIA WILLIAM",
      "grantee": "QUICKEN LOANS",
      "legal_description": "Lot 25 Block 11 Kirby Dr Sub",
      "property_address": "7870 Westheimer Rd, Houston TX 77014",
      "doc_type": "DEED OF TRUST",
      "film_code": "",
      "pages": "",
      "tax_delinquent": false,
      "code_violation": false,
      "probate_filing": false,
      "multiple_liens": false,
      "divorce_bankruptcy": false,
      "seller_score": 15,
      "days_on_record": 456,
      "maps_url": "https://www.google.com/maps/search/?api=1&query=GARCIA%20WILLIAM%2C%20Houston%2C%20TX",
      "scraped_at": "2026-04-16T03:27:37.250269",
      "source_url": "https://www.cclerk.hctx.net/applications/websearch/RP.aspx"
    },
    {
      "document_number": "2024-253343",
      "file_date": "03/01/2025",
      "grantor": "GARCIA JAMES",
      "grantee": "JP MORGAN CHASE",
      "legal_description": "Lot 10 Block 4 Montrose Blvd Sub",
      "property_address": "4282 Bellaire Blvd, Houston TX 77030",
      "doc_type": "DEED OF TRUST",
      "film_code": "",
      "pages": "",
      "tax_delinquent": false,
      "code_violation": false,
      "probate_filing": false,
      "multiple_liens": false,
      "divorce_bankruptcy": false,
      "seller_score": 15,
      "days_on_record": 411,
      "maps_url": "https://www.google.com/maps/search/?api=1&query=GARCIA%20JAMES%2C%20Houston%2C%20TX",
      "scraped_at": "2026-04-16T03:27:37.250695",
      "source_url": "https://www.cclerk.hctx.net/applications/websearch/RP.aspx"
    },
    {
      "document_number": "2024-483428",
      "file_date": "04/12/2025",
      "grantor": "JONES ELIZABETH",
      "grantee": "JP MORGAN CHASE",
      "legal_description": "Lot 4 Block 15 Memorial Dr Sub",
      "property_address": "4474 Westheimer Rd, Houston TX 77025",
      "doc_type": "DEED OF TRUST",
      "film_code": "",
      "pages": "",
      "tax_delinquent": false,
      "code_violation": false,
      "probate_filing": false,
      "multiple_liens": false,
      "divorce_bankruptcy": false,
      "seller_score": 15,
      "days_on_record": 369,
      "maps_url": "https://www.google.com/maps/search/?api=1&query=JONES%20ELIZABETH%2C%20Houston%2C%20TX",
      "scraped_at": "2026-04-16T03:27:37.250741",
      "source_url": "https://www.cclerk.hctx.net/applications/websearch/RP.aspx"
    },
    {
      "document_number": "2024-707986",
      "file_date": "07/24/2024",
      "grantor": "INTERNAL REVENUE SERVICE",
      "grantee": "BROWN BARBARA",
      "legal_description": "Lot 2 Block 9 Montrose Blvd Sub",
      "property_address": "5360 Richmond Ave, Houston TX 77081",
      "doc_type": "DEED OF TRUST",
      "film_code": "",
      "pages": "",
      "tax_delinquent": false,
      "code_violation": false,
      "probate_filing": false,
      "multiple_liens": false,
      "divorce_bankruptcy": false,
      "seller_score": 15,
      "days_on_record": 631,
      "maps_url": "https://www.google.com/maps/search/?api=1&query=INTERNAL%20REVENUE%20SERVICE%2C%20Houston%2C%20TX",
      "scraped_at": "2026-04-16T03:27:37.250832",
      "source_url": "https://www.cclerk.hctx.net/applications/websearch/RP.aspx"
    },
    {
      "document_number": "2024-884449",
      "file_date": "01/06/2025",
      "grantor": "US BANK NA",
      "grantee": "WELLS FARGO BANK",
      "legal_description": "Lot 19 Block 1 Westheimer Rd Sub",
      "property_address": "6673 Montrose Blvd, Houston TX 77087",
      "doc_type": "DEED",
      "film_code": "",
      "pages": "",
      "tax_delinquent": false,
      "code_violation": false,
      "probate_filing": false,
      "multiple_liens": false,
      "divorce_bankruptcy": false,
      "seller_score": 15,
      "days_on_record": 465,
      "maps_url": "https://www.google.com/maps/search/?api=1&query=US%20BANK%20NA%2C%20Houston%2C%20TX",
      "scraped_at": "2026-04-16T03:27:37.250852",
      "source_url": "https://www.cclerk.hctx.net/applications/websearch/RP.aspx"
    },
    {
      "document_number": "2024-344386",
      "file_date": "12/18/2024",
      "grantor": "INTERNAL REVENUE SERVICE",
      "grantee": "JONES BARBARA",
      "legal_description": "Lot 9 Block 12 Memorial Dr Sub",
      "property_address": "1579 Memorial Dr, Houston TX 77089",
      "doc_type": "DEED",
      "film_code": "",
      "pages": "",
      "tax_delinquent": false,
      "code_violation": false,
      "probate_filing": false,
      "multiple_liens": false,
      "divorce_bankruptcy": false,
      "seller_score": 15,
      "days_on_record": 484,
      "maps_url": "https://www.google.com/maps/search/?api=1&query=INTERNAL%20REVENUE%20SERVICE%2C%20Houston%2C%20TX",
      "scraped_at": "2026-04-16T03:27:37.250893",
      "source_url": "https://www.cclerk.hctx.net/applications/websearch/RP.aspx"
    },
    {
      "document_number": "2024-384032",
      "file_date": "07/23/2024",
      "grantor": "JP MORGAN CHASE",
      "grantee": "WILSON PATRICIA",
      "legal_description": "Lot 13 Block 9 Kirby Dr Sub",
      "property_address": "7519 Bellaire Blvd, Houston TX 77024",
      "doc_type": "DEED",
      "film_code": "",
      "pages": "",
      "tax_delinquent": false,
      "code_violation": false,
      "probate_filing": false,
      "multiple_liens": false,
      "divorce_bankruptcy": false,
      "seller_score": 15,
      "days_on_record": 632,
      "maps_url": "https://www.google.com/maps/search/?api=1&query=JP%20MORGAN%20CHASE%2C%20Houston%2C%20TX",
      "scraped_at": "2026-04-16T03:27:37.251131",
      "source_url": "https://www.cclerk.hctx.net/applications/websearch/RP.aspx"
    },
    {
      "document_number": "2024-604582",
      "file_date": "05/12/2025",
      "grantor": "INTERNAL REVENUE SERVICE",
      "grantee": "WILSON ROBERT",
      "legal_description": "Lot 21 Block 15 Memorial Dr Sub",
      "property_address": "177 Memorial Dr, Houston TX 77038",
      "doc_type": "DEED OF TRUST",
      "film_code": "",
      "pages": "",
      "tax_delinquent": false,
      "code_violation": false,
      "probate_filing": false,
      "multiple_liens": false,
      "divorce_bankruptcy": false,
      "seller_score": 10,
      "days_on_record": 339,
      "maps_url": "https://www.google.com/maps/search/?api=1&query=INTERNAL%20REVENUE%20SERVICE%2C%20Houston%2C%20TX",
      "scraped_at": "2026-04-16T03:27:37.250132",
      "source_url": "https://www.cclerk.hctx.net/applications/websearch/RP.aspx"
    },
    {
      "document_number": "2024-769107",
      "file_date": "07/20/2025",
      "grantor": "JOHNSON JAMES",
      "grantee": "WILLIAMS MARIA",
      "legal_description": "Lot 6 Block 12 Bellaire Blvd Sub",
      "property_address": "7806 Westheimer Rd, Houston TX 77087",
      "doc_type": "DEED",
      "film_code": "",
      "pages": "",
      "tax_delinquent": false,
      "code_violation": false,
      "probate_filing": false,
      "multiple_liens": false,
      "divorce_bankruptcy": false,
      "seller_score": 10,
      "days_on_record": 270,
      "maps_url": "https://www.google.com/maps/search/?api=1&query=JOHNSON%20JAMES%2C%20Houston%2C%20TX",
      "scraped_at": "2026-04-16T03:27:37.250158",
      "source_url": "https://www.cclerk.hctx.net/applications/websearch/RP.aspx"
    },
    {
      "document_number": "2024-662051",
      "file_date": "05/20/2025",
      "grantor": "US BANK NA",
      "grantee": "JP MORGAN CHASE",
      "legal_description": "Lot 14 Block 14 Westheimer Rd Sub",
      "property_address": "5068 Richmond Ave, Houston TX 77050",
      "doc_type": "DEED OF TRUST",
      "film_code": "",
      "pages": "",
      "tax_delinquent": false,
      "code_violation": false,
      "probate_filing": false,
      "multiple_liens": false,
      "divorce_bankruptcy": false,
      "seller_score": 10,
      "days_on_record": 331,
      "maps_url": "https://www.google.com/maps/search/?api=1&query=US%20BANK%20NA%2C%20Houston%2C%20TX",
      "scraped_at": "2026-04-16T03:27:37.250316",
      "source_url": "https://www.cclerk.hctx.net/applications/websearch/RP.aspx"
    },
    {
      "document_number": "2024-949642",
      "file_date": "05/10/2025",
      "grantor": "STATE OF TEXAS",
      "grantee": "ANDERSON ELIZABETH",
      "legal_description": "Lot 14 Block 7 Westheimer Rd Sub",
      "property_address": "4073 Shepherd Dr, Houston TX 77088",
      "doc_type": "DEED",
      "film_code": "",
      "pages": "",
      "tax_delinquent": false,
      "code_violation": false,
      "probate_filing": false,
      "multiple_liens": false,
      "divorce_bankruptcy": false,
      "seller_score": 10,
      "days_on_record": 341,
      "maps_url": "https://www.google.com/maps/search/?api=1&query=STATE%20OF%20TEXAS%2C%20Houston%2C%20TX",
      "scraped_at": "2026-04-16T03:27:37.250810",
      "source_url": "https://www.cclerk.hctx.net/applications/websearch/RP.aspx"
    },
    {
      "document_number": "2024-576001",
      "file_date": "08/05/2025",
      "grantor": "WELLS FARGO BANK",
      "grantee": "JP MORGAN CHASE",
      "legal_description": "Lot 4 Block 14 Richmond Ave Sub",
      "property_address": "8042 Westheimer Rd, Houston TX 77057",
      "doc_type": "DEED OF TRUST",
      "film_code": "",
      "pages": "",
      "tax_delinquent": false,
      "code_violation": false,
      "probate_filing": false,
      "multiple_liens": false,
      "divorce_bankruptcy": false,
      "seller_score": 10,
      "days_on_record": 254,
      "maps_url": "https://www.google.com/maps/search/?api=1&query=WELLS%20FARGO%20BANK%2C%20Houston%2C%20TX",
      "scraped_at": "2026-04-16T03:27:37.250872",
      "source_url": "https://www.cclerk.hctx.net/applications/websearch/RP.aspx"
    },
    {
      "document_number": "2024-798056",
      "file_date": "11/12/2025",
      "grantor": "STATE OF TEXAS",
      "grantee": "BROWN ELIZABETH",
      "legal_description": "Lot 16 Block 1 Bellaire Blvd Sub",
      "property_address": "4609 Bellaire Blvd, Houston TX 77091",
      "doc_type": "DEED",
      "film_code": "",
      "pages": "",
      "tax_delinquent": false,
      "code_violation": false,
      "probate_filing": false,
      "multiple_liens": false,
      "divorce_bankruptcy": false,
      "seller_score": 5,
      "days_on_record": 155,
      "maps_url": "https://www.google.com/maps/search/?api=1&query=STATE%20OF%20TEXAS%2C%20Houston%2C%20TX",
      "scraped_at": "2026-04-16T03:27:37.250222",
      "source_url": "https://www.cclerk.hctx.net/applications/websearch/RP.aspx"
    },
    {
      "document_number": "2024-475368",
      "file_date": "01/17/2026",
      "grantor": "WILLIAMS PATRICIA",
      "grantee": "JONES JAMES",
      "legal_description": "Lot 15 Block 3 Richmond Ave Sub",
      "property_address": "669 Memorial Dr, Houston TX 77015",
      "doc_type": "DEED",
      "film_code": "",
      "pages": "",
      "tax_delinquent": false,
      "code_violation": false,
      "probate_filing": false,
      "multiple_liens": false,
      "divorce_bankruptcy": false,
      "seller_score": 0,
      "days_on_record": 89,
      "maps_url": "https://www.google.com/maps/search/?api=1&query=WILLIAMS%20PATRICIA%2C%20Houston%2C%20TX",
      "scraped_at": "2026-04-16T03:27:37.250671",
      "source_url": "https://www.cclerk.hctx.net/applications/websearch/RP.aspx"
    }
  ]
}